pip_services4_memcached/__init__.py
pip_services4_memcached/build/DefaultMemcachedFactory.py
pip_services4_memcached/build/__init__.py
pip_services4_memcached/cache/MemcachedCache.py
pip_services4_memcached/cache/__init__.py
pip_services4_memcached/lock/MemcachedLock.py
pip_services4_memcached/lock/__init__.py
pip_services4_memcached-0.0.1.dist-info/LICENSE
pip_services4_memcached-0.0.1.dist-info/METADATA
pip_services4_memcached-0.0.1.dist-info/WHEEL
pip_services4_memcached-0.0.1.dist-info/top_level.txt
pip_services4_memcached-0.0.1.dist-info/zip-safe
pip_services4_memcached-0.0.1.dist-info/RECORD
